thonnycontrib/thonny_codegrinder_plugin/__init__.py
thonnycontrib/thonny_codegrinder_plugin/tkhtmlview/__init__.py
thonnycontrib/thonny_codegrinder_plugin/tkhtmlview/html_parser.py
thonny_codegrinder_plugin-2.7.1.dist-info/METADATA
thonny_codegrinder_plugin-2.7.1.dist-info/WHEEL
thonny_codegrinder_plugin-2.7.1.dist-info/top_level.txt
thonny_codegrinder_plugin-2.7.1.dist-info/RECORD
